frontmatter_to_csv/__init__.py
frontmatter_to_csv/convert.py
frontmatter_to_csv-0.2.0.dist-info/LICENSE
frontmatter_to_csv-0.2.0.dist-info/METADATA
frontmatter_to_csv-0.2.0.dist-info/WHEEL
frontmatter_to_csv-0.2.0.dist-info/entry_points.txt
frontmatter_to_csv-0.2.0.dist-info/top_level.txt
frontmatter_to_csv-0.2.0.dist-info/RECORD
