Metadata-Version: 2.1
Name: frontmatter-to-csv
Version: 0.2.0
Summary: Convert YAML front matter to CSV
Home-page: https://git.kucharczyk.xyz/lukas/frontmatter-to-csv
Author: Lukáš Kucharczyk
Author-email: lukas@kucharczyk.xyz
License: UNKNOWN
Project-URL: Bug Tracker, https://git.kucharczyk.xyz/lukas/frontmatter-to-csv/issues
Platform: UNKNOWN
Classifier: Programming Language :: Python :: 3
Classifier: Environment :: Console
Classifier: Intended Audience :: End Users/Desktop
Classifier: License :: OSI Approved :: GNU General Public License (GPL)
Classifier: Operating System :: OS Independent
Classifier: Topic :: Utilities
Requires-Python: >=3.6
License-File: LICENSE
